ollala/__init__.py
ollala/client.py
ollala-0.2.1.dist-info/LICENSE
ollala-0.2.1.dist-info/METADATA
ollala-0.2.1.dist-info/WHEEL
ollala-0.2.1.dist-info/RECORD
